<?xml version="1.0" encoding="UTF-8"?>
<objects serializationModel="Studio.01.10.00">
    <object class="EncodingSetting" id="{49a0ee8b-f965-4d73-8530-987cfe009667}">
        <property name="encodingFormat">
            <value>3</value>
        </property>
        <property name="quality">
            <value>37</value>
        </property>
        <relationship name="platform">
            <destination>{35df4280-80c1-49ed-bb1e-fd1e8ed7bdf7}</destination>
        </relationship>
        <relationship name="encodable">
            <destination>{35df4280-80c1-49ed-bb1e-fd1e8ed7bdf7}</destination>
        </relationship>
    </object>
</objects>
